{
  "id": "intro-intermediate",
  "title": "Introduction to Physical AI & Humanoid Robotics (Intermediate Level)",
  "description": "Concept",
  "source": "@site/docs-personalized/intro-intermediate.md",
  "sourceDirName": ".",
  "slug": "/intro-intermediate",
  "permalink": "/docs/personalized-intermediate/intro-intermediate",
  "draft": false,
  "unlisted": false,
  "tags": [],
  "version": "current",
  "frontMatter": {},
  "sidebar": "tutorialSidebar",
  "previous": {
    "title": "Capstone Project: Building an Autonomous Humanoid Robot (Intermediate Level)",
    "permalink": "/docs/personalized-intermediate/capstone/autonomous-humanoid-intermediate"
  },
  "next": {
    "title": "Chapter 1: The Robotic Nervous System (Intermediate Level)",
    "permalink": "/docs/personalized-intermediate/module1-the-robotic-nervous-system-intermediate"
  }
}